foxplot/__init__.py
foxplot/cli.py
foxplot/decode.py
foxplot/exceptions.py
foxplot/fox.py
foxplot/functions.py
foxplot/hot_series.py
foxplot/labeled_series.py
foxplot/node.py
foxplot/series.py
foxplot/write_tmpfile.py
foxplot/decoders/__init__.py
foxplot/decoders/json.py
foxplot/decoders/msgpack.py
foxplot-2.1.0.dist-info/entry_points.txt
foxplot-2.1.0.dist-info/licenses/LICENSE
foxplot-2.1.0.dist-info/WHEEL
foxplot-2.1.0.dist-info/METADATA
foxplot-2.1.0.dist-info/RECORD
