Metadata-Version: 2.4
Name: foxplot
Version: 2.1.0
Summary: Plot time-series data from line-delimited JSON.
Keywords: json,time,series,plot
Author-email: Stéphane Caron <stephane.caron@normalesup.org>
Maintainer-email: Stéphane Caron <stephane.caron@normalesup.org>
Requires-Python: >=3.9
Classifier: Development Status :: 4 - Beta
Classifier: Intended Audience :: Developers
Classifier: License :: OSI Approved :: GNU Lesser General Public License v3 (LGPLv3)
Classifier: Operating System :: OS Independent
Classifier: Programming Language :: Python :: 3.9
Classifier: Programming Language :: Python :: 3.10
Classifier: Programming Language :: Python :: 3.11
Classifier: Programming Language :: Python :: 3.12
Classifier: Topic :: Scientific/Engineering :: Mathematics
License-File: LICENSE
Requires-Dist: ipython >=8.0.1
Requires-Dist: msgpack >=1.0.4
Requires-Dist: numpy >=1.15.4
Requires-Dist: uplot-python >=1.0.0
Project-URL: Changelog, https://github.com/stephane-caron/foxplot/blob/master/CHANGELOG.md
Project-URL: Homepage, https://github.com/stephane-caron/foxplot
Project-URL: Source, https://github.com/stephane-caron/foxplot
Project-URL: Tracker, https://github.com/stephane-caron/foxplot/issues
